syslogfwder
