Metadata-Version: 1.1
Name: alerta-syslog
Version: 3.4.3
Summary: Alerta script for Syslog messages
Home-page: https://github.com/alerta/alerta-contrib
Author: Nick Satterly
Author-email: nick.satterly@theguardian.com
License: Apache License 2.0
Keywords: alerta syslog monitoring
Platform: UNKNOWN
Classifier: Topic :: System :: Monitoring
